cta_transit_tracker/__init__.py
cta_transit_tracker/cta_transit_exceptions.py
cta_transit_tracker/cta_transit_tracker.py
cta_transit_tracker-0.0.1.dist-info/LICENSE
cta_transit_tracker-0.0.1.dist-info/METADATA
cta_transit_tracker-0.0.1.dist-info/WHEEL
cta_transit_tracker-0.0.1.dist-info/top_level.txt
cta_transit_tracker-0.0.1.dist-info/RECORD
