Metadata-Version: 2.1
Name: cta-transit-tracker
Version: 0.0.1
Summary: An asyncronous wrapper over the Chicago Transit Authority Bus Tracker and Train Tracker APIs
Home-page: https://github.com/chalamka/cta_transit_tracker
Author: Carter Halamka
License: UNKNOWN
Platform: UNKNOWN
Classifier: Programming Language :: Python :: 3.7
Classifier: License :: OSI Approved :: MIT License
Classifier: Operating System :: OS Independent
